Aptester/__init__.py
Aptester/__main__.py
Aptester/controll.py
Aptester/core.py
ApTester-0.1.4.dist-info/LICENCE
ApTester-0.1.4.dist-info/METADATA
ApTester-0.1.4.dist-info/WHEEL
ApTester-0.1.4.dist-info/entry_points.txt
ApTester-0.1.4.dist-info/top_level.txt
ApTester-0.1.4.dist-info/RECORD
